{"expireTime":9007200867593591000,"key":"fcb478ec27f1bf1691143a38012f2adb","val":{"name":"IMAGE_PROCESSING","inputPaths":["C:/Users/AweSome/Desktop/React Website Desing/gamingtechies/static/img/gearit-50-pack-cat-5e-ethernet-patch-cable.webp"],"outputDir":"C:/Users/AweSome/Desktop/React Website Desing/gamingtechies/public/static/a0bcba49adfdaef8cc80d4b41829e258","args":{"isLazy":false,"operations":[{"outputPath":"61e93\\gearit-50-pack-cat-5e-ethernet-patch-cable.webp","args":{"width":200,"cropFocus":17,"toFormat":"webp","fit":"cover","background":"rgba(0,0,0,1)"}},{"outputPath":"403a4\\gearit-50-pack-cat-5e-ethernet-patch-cable.webp","args":{"width":300,"cropFocus":17,"toFormat":"webp","fit":"cover","background":"rgba(0,0,0,1)"}}],"pluginOptions":{"base64Width":20,"forceBase64Format":"","useMozJpeg":false,"stripMetadata":true,"lazyImageGeneration":true,"defaultQuality":50,"failOnError":true,"plugins":[]}}}}